setup.py
curl_parser/__init__.py
curl_parser/parser.py
curl_parser.egg-info/PKG-INFO
curl_parser.egg-info/SOURCES.txt
curl_parser.egg-info/dependency_links.txt
curl_parser.egg-info/requires.txt
curl_parser.egg-info/top_level.txt