Metadata-Version: 1.1
Name: curl-parser
Version: 1.0
Summary: parser module for curl command.
Home-page: https://github.com/jinniahn/curl_parser
Author: jinsub ahn
Author-email: jinniahn@gmail.com
License: MIT
Keywords: curl,network
Platform: UNKNOWN
Classifier: Topic :: Utilities
